persistentdatatools/__init__.py
persistentdatatools/persistentdatatools.py
persistentdatatools/version.py
persistentdatatools-2.2.13.dist-info/LICENSE
persistentdatatools-2.2.13.dist-info/METADATA
persistentdatatools-2.2.13.dist-info/WHEEL
persistentdatatools-2.2.13.dist-info/top_level.txt
persistentdatatools-2.2.13.dist-info/RECORD
